{
    "api": "2",
    "type": "anime",
    "name": "mandao",
    "version": "1.2",
    "muliSources": true,
    "useWebview": true,
    "useNativePlayer": true,
    "usePost": true,
    "userAgent": "",
    "baseURL": "https://www.mandaow.cc/",
    "searchURL":"https://www.mandaow.cc/search.php?searchword=@keyword",
    "searchList": "//div[2]/div[3]/ul/li",
    "searchName": "//a/div[2]/p",
    "searchResult": "//a",
    "chapterRoads": "//div[2]/div[5]/div[2]/div[2]/ul/div/ul",
    "chapterResult": "//li/a"
}