{
    "api": "6",
    "type": "anime",
    "name": "xfdmneo",
    "version": "1.1",
    "muliSources": true,
    "useWebview": true,
    "useNativePlayer": true,
    "usePost": false,
    "useLegacyParser": true,
    "adBlocker": false,
    "userAgent": "",
    "baseURL": "https://dm1.xfdm.pro/",
    "searchURL": "https://dm1.xfdm.pro/search.html?wd=@keyword",
    "searchList": "//div[@class='public-list-box search-box flex rel']",
    "searchName": "//div[3]/div[1]/div[1]",
    "searchResult": "//div[3]/div[2]/a[1]",
    "chapterRoads": "//ul[@class='anthology-list-play size']",
    "chapterResult": "//li/a",
    "referer": ""
}